README.md
setup.py
src/python_icd10/__init__.py
src/python_icd10/icd10_load.py
src/python_icd10/icd10_model.py
src/python_icd10/icd10_warehouse.py
src/python_icd10.egg-info/PKG-INFO
src/python_icd10.egg-info/SOURCES.txt
src/python_icd10.egg-info/dependency_links.txt
src/python_icd10.egg-info/requires.txt
src/python_icd10.egg-info/top_level.txt